README.md
setup.cfg
setup.py
TOPSIS_PARNEET_101803075/topsis.py
TOPSIS_PARNEET_101803075.egg-info/PKG-INFO
TOPSIS_PARNEET_101803075.egg-info/SOURCES.txt
TOPSIS_PARNEET_101803075.egg-info/dependency_links.txt
TOPSIS_PARNEET_101803075.egg-info/entry_points.txt
TOPSIS_PARNEET_101803075.egg-info/requires.txt
TOPSIS_PARNEET_101803075.egg-info/top_level.txt