Metadata-Version: 2.1
Name: TOPSIS-PARNEET-101803075
Version: 1.1.0
Summary: A Python package for topsis analysis.
Home-page: UNKNOWN
Author: Parneet Kaur
Author-email: parneetkaurr106@gmail.com
License: MIT
Platform: UNKNOWN
Classifier: License :: OSI Approved :: MIT License
Classifier: Programming Language :: Python :: 3
Classifier: Programming Language :: Python :: 3.7
